nanonetsclient/__init__.py
nanonetsclient/client.py
nanonetsclient-1.0.4.dist-info/LICENSE
nanonetsclient-1.0.4.dist-info/METADATA
nanonetsclient-1.0.4.dist-info/WHEEL
nanonetsclient-1.0.4.dist-info/top_level.txt
nanonetsclient-1.0.4.dist-info/RECORD
