Metadata-Version: 2.1
Name: nanonetsclient
Version: 1.0.4
Summary: Nanonets API SDK for Python
Home-page: https://nanonets.com/?utm_source=python-sdk&utm_medium=sdk&utm_campaign=sdk-install&ph_source=python-sdk&ph_medium=sdk&ph_campaign=sdk-install
Author: Nanonets
Author-email: support@nanonets.com
Classifier: Programming Language :: Python :: 3
Classifier: Programming Language :: Python :: 3.7
Classifier: Programming Language :: Python :: 3.8
Classifier: Programming Language :: Python :: 3.9
Classifier: Programming Language :: Python :: 3.10
Classifier: License :: OSI Approved :: MIT License
Classifier: Operating System :: OS Independent
Requires-Python: >=3.7
License-File: LICENSE
Requires-Dist: requests >=2.25.0
Requires-Dist: python-dotenv >=0.19.0
